funnylog2/__init__.py
funnylog2/__version__.py
funnylog2/config.py
funnylog2-2024.10.26.dist-info/METADATA
funnylog2-2024.10.26.dist-info/WHEEL
funnylog2-2024.10.26.dist-info/licenses/LICENSE
funnylog2-2024.10.26.dist-info/RECORD
