Metadata-Version: 2.1
Name: funnylog2
Version: 2024.10.26
Author-email: mikigo <huangmingqiang@uniontech.com>
License: GPL2.0
License-File: LICENSE
Requires-Python: >=3.6
Provides-Extra: allure
Requires-Dist: allure-pytest; extra == 'allure'
